selectorcolor/__init__.py
selectorcolor/selectorcolor.py
selectorcolor/selectorcolor2.py
selectorcolor/selectorcolor3.py
selectorcolor/seletor_de_cores.py
selectorcolor/Temas.plk
selectorcolor/Temas.py
selectorcolor/teste_selector.py
selectorcolor/themeload.py
selectorcolor-0.1.25.dist-info/METADATA
selectorcolor-0.1.25.dist-info/WHEEL
selectorcolor-0.1.25.dist-info/RECORD
