Metadata-Version: 2.1
Name: selectorcolor
Version: 0.1.25
Summary: 
Author: leomoraesguitar
Author-email: 123950901+leomoraesguitar@users.noreply.github.com
Requires-Python: >=3.12,<4.0
Classifier: Programming Language :: Python :: 3
Classifier: Programming Language :: Python :: 3.12
Requires-Dist: flet (>=0.27.1,<0.28.0)
